linearagent/__init__.py
linearagent/linearagent.py
linearagent/memory.py
linearagent/tool.py
linearagent-0.0.2.dist-info/LICENSE
linearagent-0.0.2.dist-info/METADATA
linearagent-0.0.2.dist-info/WHEEL
linearagent-0.0.2.dist-info/entry_points.txt
linearagent-0.0.2.dist-info/top_level.txt
linearagent-0.0.2.dist-info/RECORD
